[
  {
    "name": "Worlders",
    "diff": "MAS",
    "level": "12+",
    "url": "https://sdvx.in//chunithm/10/10158mst.htm"
  },
  {
    "name": "はじまりの未来",
    "diff": "MAS",
    "level": "12+",
    "url": "https://sdvx.in//chunithm/10/10157mst.htm"
  },
  {
    "name": "Galaxy Collapse",
    "diff": "MAS",
    "level": "15",
    "url": "https://sdvx.in//chunithm/10/10161mst.htm"
  },
  {
    "name": "Idoratrize World",
    "diff": "MAS",
    "level": "14",
    "url": "https://sdvx.in//chunithm/10/10159mst.htm"
  },
  {
    "name": "Necromantic",
    "diff": "MAS",
    "level": "13",
    "url": "https://sdvx.in//chunithm/10/10160mst.htm"
  }
]